webvpn_ng/__init__.py
webvpn_ng/chisel.py
webvpn_ng/cmd.py
webvpn_ng/login.py
webvpn_ng/utils.py
webvpn_ng-0.1.2.dist-info/METADATA
webvpn_ng-0.1.2.dist-info/WHEEL
webvpn_ng-0.1.2.dist-info/entry_points.txt
webvpn_ng-0.1.2.dist-info/RECORD
