Metadata-Version: 2.1
Name: webvpn-ng
Version: 0.1.2
Summary: 
License: MIT
Author: Ming Yang
Author-email: ymviv@qq.com
Requires-Python: >=3.8,<4.0
Classifier: License :: OSI Approved :: MIT License
Classifier: Programming Language :: Python :: 3
Classifier: Programming Language :: Python :: 3.8
Classifier: Programming Language :: Python :: 3.9
Classifier: Programming Language :: Python :: 3.10
Classifier: Programming Language :: Python :: 3.11
Requires-Dist: beautifulsoup4 (>=4.11.2,<5.0.0)
Requires-Dist: requests (>=2.28.2,<3.0.0)
Requires-Dist: typer[all] (>=0.7.0,<0.8.0)
